{
    "default-registry": {
        "kind": "git",
        "repository": "https://github.com/microsoft/vcpkg.git",
        "baseline": "80ecf32496c3806c5bb79bb80f029f83d058930e"
    },
    "registries": [
        {
            "kind": "git",
            "repository": "https://github.com/libsese/vcpkg-registry.git",
            "baseline": "3662debb1932b134da886e3d1335ce274680d36a",
            "packages": [
                "simpleuuid",
                "sstring",
                "sese-plugin",
                "sese-event",
                "sese"
            ]
        }
    ]
}